pyasr/__init__.py
pyasr/__version__.py
pyasr/asr.py
pyasr/gaps.py
pyasr/read.py
pyasr/dat/MtZoa.dat
pyasr/dat/cpREV10.dat
pyasr/dat/cpREV64.dat
pyasr/dat/dayhoff-dcmut.dat
pyasr/dat/dayhoff.dat
pyasr/dat/g1974a.dat
pyasr/dat/g1974c.dat
pyasr/dat/g1974p.dat
pyasr/dat/g1974v.dat
pyasr/dat/grantham.dat
pyasr/dat/jones-dcmut.dat
pyasr/dat/jones.dat
pyasr/dat/lg.dat
pyasr/dat/miyata.dat
pyasr/dat/mtArt.dat
pyasr/dat/mtREV24.dat
pyasr/dat/mtmam.dat
pyasr/dat/wag.dat
pyasr-0.6.1.dist-info/METADATA
pyasr-0.6.1.dist-info/RECORD
pyasr-0.6.1.dist-info/WHEEL
pyasr-0.6.1.dist-info/top_level.txt
