Metadata-Version: 2.1
Name: pyasr
Version: 0.6.1
Summary: Ancestral sequence reconstruction using Python
Home-page: https://github.com/Zsailer/pyasr
Author: Zachary Sailer
Author-email: zachsailer@gmail.com
License: MIT
Platform: UNKNOWN
Classifier: License :: OSI Approved :: MIT License
Classifier: Programming Language :: Python
Classifier: Programming Language :: Python :: 3
Classifier: Programming Language :: Python :: 3.6
Classifier: Programming Language :: Python :: Implementation :: CPython
Classifier: Programming Language :: Python :: Implementation :: PyPy
Requires-Python: >=3.0.0
